si_converter/__init__.py
si_converter/fromSI/__init__.py
si_converter/fromSI/from_si_converter.py
si_converter/toSI/__init__.py
si_converter/toSI/to_si_converter.py
SI_converter-2.0.0.dist-info/METADATA
SI_converter-2.0.0.dist-info/WHEEL
SI_converter-2.0.0.dist-info/top_level.txt
SI_converter-2.0.0.dist-info/RECORD
