Metadata-Version: 2.1
Name: SI_converter
Version: 2.0.0
Home-page: 
Author: Yanuskevich M.D.
Author-email: mikhal_2005@mail.ru
Keywords: system si converter
Classifier: Programming Language :: Python :: 3.12
Classifier: License :: OSI Approved :: MIT License
Classifier: Operating System :: OS Independent
Requires-Python: >=3.7
